echo_display.v
`include "echo_codificador.v"

module echo_display (
    input SD1,
    input SD2,
    input SD3,
    input SD4,
    input SD5,
    output a,
    output b,
    output c,
    output d,
    output e,
    output f,
    output g
);

    assign a = (~SD1 | SD5 | (SD2 & ~SD4));
    assign b = (~SD2 | ~SD5);
    assign c = (~SD2 | SD3);
    assign d = ((~SD1 & ~SD3) | (SD2 & ~SD4) | (SD2 & SD5));
    assign e = ((~SD1 & ~SD5) | (~SD3 & SD4) | (~SD1 & SD2) | (SD2 & ~SD3));
    assign f = ((~SD1 & ~SD3) | (SD2 & SD4));
    assign g = ((~SD3 & SD5) | SD2);

endmodule

echo_codificador.v
module echo_codificador (
  input RE,
  input RS,
  input A,
  input B,
  input C,
  input D,
  output S1,
  output S2,
  output S3,
  output S4,
  output S5
);

  assign S1 = ((RE & ~RS & ~B & ~C & ~D) | (RE & ~RS & ~A & B & C) | (RE & ~RS & A & ~B & ~C) | (RE & ~RS & A & ~B & ~D));
  assign S2 = ((RE & ~RS & ~B & ~C) | (RE & ~RS & ~A & B & C & D) | (RE & ~RS & A & ~B));
  assign S3 = ((RE & ~RS & ~B & ~C) | (RE & ~RS & ~B & ~D) | (RE & ~RS & A & ~B) | (RE & ~RS & A & ~C & ~D));
  assign S4 = ((RE & ~RS & ~A & ~B) | (RE & ~RS & ~B & D) | (RE & ~RS & ~B & C) | (RE & ~RS & A & B & ~C));
  assign S5 = ((RE & ~RS & ~A & ~B) | (RE & ~RS & ~A & ~C & ~D) | (RE & ~RS & ~B & C) | (RE & ~RS & A & B & ~C) | (RE & ~RS & A & B & ~D));

  
endmodule

echo_testbench.v
`include "echo_display.v"
`timescale 1us/1ns

module echo_testbanch ();
    reg RE;
    reg RS;
    reg A;
    reg B;
    reg C;
    reg D;
    reg E;
    wire S1;
    wire S2;
    wire S3;
    wire S4;
    wire S5;
    wire a;
    wire b;
    wire c;
    wire d;
    wire e;
    wire f;
    wire g;
    

 
    echo_codificador link_codificador (
        .RE(RE),
        .RS(RS),
        .A(A),
        .B(B),
        .C(C),
        .D(D),
        .S1(S1),
        .S2(S2),
        .S3(S3), 
        .S4(S4),
        .S5(S5)
    );

    echo_display link_display (
        .SD1(S1),
        .SD2(S2),
        .SD3(S3),
        .SD4(S4),
        .SD5(S5),
        .a(a),
        .b(b),
        .c(c),
        .d(d),
        .e(e),
        .f(f),
        .g(g)
    );

    reg [5:0] teste[0:16];
    integer cont;
    
    initial begin
        $dumpfile("echo_GTKWAVES.vcd");
        $dumpvars();
        teste[0] = 6'b100000;
        teste[1] = 6'b100001;
        teste[2] = 6'b100010;
        teste[3] = 6'b100011;
        teste[4] = 6'b100100;
        teste[5] = 6'b100101;
        teste[6] = 6'b100110;
        teste[7] = 6'b100111;
        teste[8] = 6'b101000;
        teste[9] = 6'b101001;
        teste[10] = 6'b101010;
        teste[11] = 6'b101011;
        teste[12] = 6'b101100;
        teste[13] = 6'b101101;
        teste[14] = 6'b101110;
        teste[15] = 6'b101111;
        for (cont = 0; cont < 16; cont = cont + 1)
        begin
            RE = teste[cont][5];
            RS = teste[cont][4];
            A = teste[cont][3];
            B = teste[cont][2];
            C = teste[cont][1];
            D = teste[cont][0];
            #10;
            $display("Entrada: %d %d %d %d %d %d", RE, RS, A, B, C, D);
            $display("Codificado: %d %d %d %d %d", S1, S2, S3, S4, S5);
            $display("Display: %d %d %d %d %d %d %d", a, b, c, d, e, f, g);
            $display("\n");
        end
    end
endmodule

echo_GTKWAVES.vcd
$date
	Mon Oct 24 02:14:47 2022
$end
$version
	Icarus Verilog
$end
$timescale
	1ns
$end
$scope module echo_testbanch $end
$var wire 1 ! S1 $end
$var wire 1 " S2 $end
$var wire 1 # S3 $end
$var wire 1 $ S4 $end
$var wire 1 % S5 $end
$var wire 1 & a $end
$var wire 1 ' b $end
$var wire 1 ( c $end
$var wire 1 ) d $end
$var wire 1 * e $end
$var wire 1 + f $end
$var wire 1 , g $end
$var reg 1 - A $end
$var reg 1 . B $end
$var reg 1 / C $end
$var reg 1 0 D $end
$var reg 1 1 RE $end
$var reg 1 2 RS $end
$var integer 32 3 cont [31:0] $end
$scope module link_codificador $end
$var wire 1 4 A $end
$var wire 1 5 B $end
$var wire 1 6 C $end
$var wire 1 7 D $end
$var wire 1 8 RE $end
$var wire 1 9 RS $end
$var wire 1 ! S1 $end
$var wire 1 " S2 $end
$var wire 1 # S3 $end
$var wire 1 $ S4 $end
$var wire 1 % S5 $end
$upscope $end
$scope module link_display $end
$var wire 1 ! SD1 $end
$var wire 1 " SD2 $end
$var wire 1 # SD3 $end
$var wire 1 $ SD4 $end
$var wire 1 % SD5 $end
$var wire 1 & a $end
$var wire 1 ' b $end
$var wire 1 ( c $end
$var wire 1 ) d $end
$var wire 1 * e $end
$var wire 1 + f $end
$var wire 1 , g $end
$upscope $end
$upscope $end
$enddefinitions $end
#0
$dumpvars
09
18
07
06
05
04
b0 3
02
11
00
0/
0.
0-
1,
1+
0*
1)
1(
0'
1&
1%
1$
1#
1"
1!
$end
#10000
1*
0!
10
17
b1 3
#20000
0*
1'
0)
0+
0,
0"
00
07
1/
16
b10 3
#30000
1*
1)
1+
1,
0#
10
17
b11 3
#40000
0*
0$
00
07
0/
06
1.
15
b100 3
#50000
1*
0,
0%
10
17
b101 3
#60000
0*
0)
0&
0+
1!
00
07
1/
16
b110 3
#70000
1)
1&
0(
1*
1,
1"
10
17
b111 3
#80000
0*
1(
1#
00
07
0/
06
0.
05
1-
14
b1000 3
#90000
0)
0&
1+
1$
10
17
b1001 3
#100000
1&
0'
1)
1%
00
07
1/
16
b1010 3
#110000
1*
0!
10
17
b1011 3
#120000
0*
1'
0)
0+
0,
0"
00
07
0/
06
1.
15
b1100 3
#130000
1*
1)
1+
1,
0#
10
17
b1101 3
#140000
0*
0$
00
07
1/
16
b1110 3
#150000
1*
0,
0%
10
17
b1111 3
#160000
b10000 3
